{
  "countries": [
    { "value": "TR", "label": "Türkiye" },
    { "value": "US", "label": "Amerika Birleşik Devletleri" },
    { "value": "DE", "label": "Almanya" },
    { "value": "FR", "label": "Fransa" },
    { "value": "GB", "label": "Birleşik Krallık" },
    { "value": "IT", "label": "İtalya" },
    { "value": "ES", "label": "İspanya" },
    { "value": "CA", "label": "Kanada" },
    { "value": "AU", "label": "Avustralya" },
    { "value": "CN", "label": "Çin" },
    { "value": "IN", "label": "Hindistan" },
    { "value": "RU", "label": "Rusya" },
    { "value": "BR", "label": "Brezilya" },
    { "value": "MX", "label": "Meksika" },
    { "value": "ID", "label": "Endonezya" },
    { "value": "PK", "label": "Pakistan" },
    { "value": "BD", "label": "Bangladeş" },
    { "value": "NG", "label": "Nijerya" },
    { "value": "RU", "label": "Rusya" },
    { "value": "JP", "label": "Japonya" }
  ]
}
   
